{
    "keep": {
        "days": true,
        "amount": 14
    },
    "auditLog": "C:\\Users\\logga\\Documents\\ltth_codex\\ltth_desktop2-main\\logs\\.45ae4827188c18748cd62e13d5dae32c712adb55-audit.json",
    "files": [
        {
            "date": 1777407411144,
            "name": "C:\\Users\\logga\\Documents\\ltth_codex\\ltth_desktop2-main\\logs\\app-2026-04-28.log",
            "hash": "5dd0f07b62d88053885f234af5e51854d8a7ae3115479aabcd39e62e0d41e6a2"
        }
    ],
    "hashType": "sha256"
}