{
    "keep": {
        "days": true,
        "amount": 14
    },
    "auditLog": "C:\\Users\\logga\\Documents\\ltth_codex\\ltth_desktop2-main\\logs\\.45ae4827188c18748cd62e13d5dae32c712adb55-audit.json",
    "files": [
        {
            "date": 1777833350636,
            "name": "C:\\Users\\logga\\Documents\\ltth_codex\\ltth_desktop2-main\\logs\\app-2026-05-03.log",
            "hash": "f2e2ee5465acc870b37a724ae675fb7e1589261c9f094c3ee8b1c2c25e3bae02"
        },
        {
            "date": 1777846063051,
            "name": "C:\\Users\\logga\\Documents\\ltth_codex\\ltth_desktop2-main\\logs\\app-2026-05-04.log",
            "hash": "d5ead8c16c902806726fe282a2eb72250bae38c3305490162b17291f7573a38e"
        }
    ],
    "hashType": "sha256"
}