{
    "keep": {
        "days": true,
        "amount": 14
    },
    "auditLog": "C:\\Users\\logga\\Documents\\ltth_codex\\ltth_desktop2-main\\logs\\.45ae4827188c18748cd62e13d5dae32c712adb55-audit.json",
    "files": [
        {
            "date": 1777499824748,
            "name": "C:\\Users\\logga\\Documents\\ltth_codex\\ltth_desktop2-main\\logs\\app-2026-04-29.log",
            "hash": "b95344d5c31f4e3d58d1b54fa8a5f162beaca2c4c3fe1d1a091a535e18d90aa2"
        },
        {
            "date": 1777500001424,
            "name": "C:\\Users\\logga\\Documents\\ltth_codex\\ltth_desktop2-main\\logs\\app-2026-04-30.log",
            "hash": "e36f5c9c62407684a361f9647f116ab1be5947883d36896b5068692fdddb920f"
        }
    ],
    "hashType": "sha256"
}