{
    "keep": {
        "days": true,
        "amount": 14
    },
    "auditLog": "C:\\Users\\logga\\Documents\\ltth_codex\\ltth_desktop2-main\\logs\\.45ae4827188c18748cd62e13d5dae32c712adb55-audit.json",
    "files": [
        {
            "date": 1777502866087,
            "name": "C:\\Users\\logga\\Documents\\ltth_codex\\ltth_desktop2-main\\logs\\app-2026-04-30.log",
            "hash": "bb3d879c678b89fcc322a31400341704fa53478bb0d6384a921ff0316401f6f7"
        }
    ],
    "hashType": "sha256"
}